meltvid/__init__.py
meltvid/melt.py
meltvid-0.0.1.dist-info/LICENSE
meltvid-0.0.1.dist-info/METADATA
meltvid-0.0.1.dist-info/WHEEL
meltvid-0.0.1.dist-info/top_level.txt
meltvid-0.0.1.dist-info/RECORD
