Metadata-Version: 2.1
Name: meltvid
Version: 0.0.1
Summary: Video editing using MLT with Python
Home-page: https://github.com/Joemgu7/melt_python
Author: Jonas Briguet
Author-email: briguetjo@yahoo.de
Keywords: video editing
Classifier: Programming Language :: Python :: 3
Classifier: License :: OSI Approved :: MIT License
Classifier: Operating System :: OS Independent
Requires-Python: >=3.7
License-File: LICENSE
